compito/__init__.py
compito/__main__.py
compito/command.py
compito/command_manager.py
compito/schedule_manager.py
compito/scheduler.py
compito/utils.py
compito-0.2.1.dist-info/METADATA
compito-0.2.1.dist-info/WHEEL
compito-0.2.1.dist-info/RECORD
