Metadata-Version: 2.1
Name: compito
Version: 0.2.1
Summary: 
Author: iYasha
Author-email: 33287747+iYasha@users.noreply.github.com
Requires-Python: >=3.8,<4.0
Classifier: Programming Language :: Python :: 3
Classifier: Programming Language :: Python :: 3.8
Classifier: Programming Language :: Python :: 3.9
Classifier: Programming Language :: Python :: 3.10
Classifier: Programming Language :: Python :: 3.11
Classifier: Programming Language :: Python :: 3.12
Provides-Extra: croniter
Requires-Dist: croniter (>=2.0.1,<3.0.0) ; extra == "croniter"
